{"cameraMode":{"drawMode":0,"name":"Shaded","section":"Shading Mode"},"sceneLighting":true,"audioPlay":false,"sceneViewState":{"m_AlwaysRefresh":false,"showFog":true,"showSkybox":true,"showFlares":true,"showImageEffects":true,"showParticleSystems":true,"showVisualEffectGraphs":true,"m_FxEnabled":true},"in2DMode":false,"pivot":{"x":-9.606209754943848,"y":-1.2746593952178956,"z":4.734199047088623},"rotation":{"x":-0.05931168422102928,"y":0.5438084602355957,"z":-0.038571227341890338,"w":-0.8362219929695129},"size":13.96189022064209,"orthographic":false}